flux_rx/__init__.py
flux_rx/analytics.py
flux_rx/api.py
flux_rx/charts.py
flux_rx/compare.py
flux_rx/dashboard.py
flux_rx/data.py
flux_rx/report.py
flux_rx/themes.py
flux_rx-0.1.0.dist-info/METADATA
flux_rx-0.1.0.dist-info/WHEEL
flux_rx-0.1.0.dist-info/top_level.txt
flux_rx-0.1.0.dist-info/RECORD
