Metadata-Version: 2.4
Name: flux-rx
Version: 0.1.0
Summary: A stock market analysis and visualization Python package.
Author: Flux-RX Contributors
License: MIT
Project-URL: Homepage, https://github.com/flux-rx/flux-rx
Project-URL: Documentation, https://flux-rx.readthedocs.io
Keywords: finance,stocks,analysis,visualization,plotly
Classifier: Development Status :: 4 - Beta
Classifier: Intended Audience :: Financial and Insurance Industry
Classifier: License :: OSI Approved :: MIT License
Classifier: Programming Language :: Python :: 3
Classifier: Programming Language :: Python :: 3.9
Classifier: Programming Language :: Python :: 3.10
Classifier: Programming Language :: Python :: 3.11
Classifier: Programming Language :: Python :: 3.12
Classifier: Topic :: Office/Business :: Financial :: Investment
Requires-Python: >=3.9
Requires-Dist: yfinance>=0.2.0
Requires-Dist: pandas>=2.0.0
Requires-Dist: numpy>=1.24.0
Requires-Dist: plotly>=5.18.0
Requires-Dist: dash>=2.14.0
Requires-Dist: dash-bootstrap-components>=1.5.0
Requires-Dist: requests>=2.28.0
Provides-Extra: dev
Requires-Dist: pytest>=7.0.0; extra == "dev"
Requires-Dist: black>=23.0.0; extra == "dev"
Requires-Dist: ruff>=0.1.0; extra == "dev"
